{
    "_settings": {},
    "bodies": [
        {
            "angle": 0.7843743562698364,
            "p": [
                28.69001007080078,
                11.667254447937012
            ],
            "size": [
                3.0,
                0.5
            ],
            "uuid": "24a1b930-79e7-4e13-abd0-744b88521ac4"
        },
        {
            "angle": -1.1845463276927148e-08,
            "p": [
                33.32915496826172,
                13.535272598266602
            ],
            "size": [
                3.0,
                0.5
            ],
            "uuid": "cbd16026-bd41-47f2-a15e-a9cfe436a138"
        },
        {
            "angle": -0.7667957544326782,
            "p": [
                38.072261810302734,
                11.61138916015625
            ],
            "size": [
                3.0,
                0.5
            ],
            "uuid": "2dac4675-af87-4eca-93d4-93dcd6020bf2"
        },
        {
            "angle": 0.18682822585105896,
            "p": [
                27.19158363342285,
                8.189842224121094
            ],
            "size": [
                0.25,
                1.75
            ],
            "uuid": "77c77f9e-3488-433e-9c43-237688dad2ee"
        },
        {
            "angle": -0.24121399223804474,
            "p": [
                39.52162170410156,
                8.20113468170166
            ],
            "size": [
                0.25,
                1.75
            ],
            "uuid": "82ff7aba-2ae4-4aeb-838e-cf561b4ef689"
        }
    ],
    "joints": [
        {
            "a_uuid": "24a1b930-79e7-4e13-abd0-744b88521ac4",
            "b_uuid": "cbd16026-bd41-47f2-a15e-a9cfe436a138",
            "ll": -0.15707963705062866,
            "p": [
                30.700000762939453,
                13.399999618530273
            ],
            "ul": 0.15707963705062866
        },
        {
            "a_uuid": "cbd16026-bd41-47f2-a15e-a9cfe436a138",
            "b_uuid": "2dac4675-af87-4eca-93d4-93dcd6020bf2",
            "ll": -0.15707963705062866,
            "p": [
                36.099998474121094,
                13.399999618530273
            ],
            "ul": 0.15707963705062866
        },
        {
            "a_uuid": "24a1b930-79e7-4e13-abd0-744b88521ac4",
            "b_uuid": "77c77f9e-3488-433e-9c43-237688dad2ee",
            "ll": -0.3141592741012573,
            "p": [
                26.950000762939453,
                9.550000190734863
            ],
            "ul": 0.3141592741012573
        },
        {
            "a_uuid": "2dac4675-af87-4eca-93d4-93dcd6020bf2",
            "b_uuid": "82ff7aba-2ae4-4aeb-838e-cf561b4ef689",
            "ll": -0.3141592741012573,
            "p": [
                39.900001525878906,
                9.449999809265137
            ],
            "ul": 0.3141592741012573
        }
    ]
}