{
    "_settings": {},
    "bodies": [
        {
            "angle": 3.084205389022827,
            "p": [
                36.42634963989258,
                17.60801887512207
            ],
            "size": [
                1.75,
                0.75
            ],
            "uuid": "4548e315-7063-4413-aa70-9ea89c9f96d6"
        },
        {
            "angle": 0.8705253601074219,
            "p": [
                34.36594009399414,
                16.555063247680664
            ],
            "size": [
                1.25,
                0.5
            ],
            "uuid": "738ea919-6f9c-4f33-afbe-b3206d9c2a48"
        },
        {
            "angle": 0.14430102705955505,
            "p": [
                32.58903503417969,
                14.48488712310791
            ],
            "size": [
                1.5,
                1.5
            ],
            "uuid": "b625be94-cf6e-4e54-b494-4155abcd9bbd"
        },
        {
            "angle": -0.09225241839885712,
            "p": [
                28.542003631591797,
                14.659928321838379
            ],
            "size": [
                3.0,
                1.25
            ],
            "uuid": "04ba9991-2069-4fa9-9f71-aae2db577742"
        },
        {
            "angle": 0.2885604798793793,
            "p": [
                26.79686737060547,
                12.82099723815918
            ],
            "size": [
                0.75,
                2.25
            ],
            "uuid": "02cceb96-ac9d-4d48-92cf-62f89c511b74"
        },
        {
            "angle": -0.3283529579639435,
            "p": [
                26.76104164123535,
                8.83319091796875
            ],
            "size": [
                0.5,
                2.5
            ],
            "uuid": "998dd1c3-ca90-4d9b-8fee-cec84fd81a24"
        },
        {
            "angle": -0.39257073402404785,
            "p": [
                32.961666107177734,
                11.882224082946777
            ],
            "size": [
                0.5,
                2.0
            ],
            "uuid": "166841b5-9f81-440d-91d8-2f76b73cc446"
        },
        {
            "angle": 0.49714601039886475,
            "p": [
                33.24178695678711,
                8.448479652404785
            ],
            "size": [
                0.5,
                2.25
            ],
            "uuid": "b5f2b952-4563-4a78-9369-3029a97c1ec2"
        },
        {
            "angle": -0.846140444278717,
            "p": [
                24.557077407836914,
                17.2215633392334
            ],
            "size": [
                2.25,
                0.25
            ],
            "uuid": "170d0b73-b140-43df-bee9-edf41ea409fa"
        },
        {
            "angle": -3.4061942100524902,
            "p": [
                23.477367401123047,
                19.467208862304688
            ],
            "size": [
                0.25,
                1.0
            ],
            "uuid": "3edf09c8-6d27-4d28-8b51-b65122ec9129"
        }
    ],
    "joints": [
        {
            "a_uuid": "b625be94-cf6e-4e54-b494-4155abcd9bbd",
            "b_uuid": "166841b5-9f81-440d-91d8-2f76b73cc446",
            "p": [
                33.650001525878906,
                13.399999618530273
            ]
        },
        {
            "a_uuid": "04ba9991-2069-4fa9-9f71-aae2db577742",
            "b_uuid": "02cceb96-ac9d-4d48-92cf-62f89c511b74",
            "p": [
                26.450000762939453,
                14.600000381469727
            ]
        },
        {
            "a_uuid": "02cceb96-ac9d-4d48-92cf-62f89c511b74",
            "b_uuid": "998dd1c3-ca90-4d9b-8fee-cec84fd81a24",
            "p": [
                27.549999237060547,
                10.949999809265137
            ]
        },
        {
            "a_uuid": "04ba9991-2069-4fa9-9f71-aae2db577742",
            "b_uuid": "170d0b73-b140-43df-bee9-edf41ea409fa",
            "p": [
                25.950000762939453,
                15.800000190734863
            ]
        },
        {
            "a_uuid": "170d0b73-b140-43df-bee9-edf41ea409fa",
            "b_uuid": "3edf09c8-6d27-4d28-8b51-b65122ec9129",
            "p": [
                23.299999237060547,
                18.649999618530273
            ]
        },
        {
            "a_uuid": "4548e315-7063-4413-aa70-9ea89c9f96d6",
            "b_uuid": "738ea919-6f9c-4f33-afbe-b3206d9c2a48",
            "p": [
                34.900001525878906,
                17.200000762939453
            ]
        },
        {
            "a_uuid": "738ea919-6f9c-4f33-afbe-b3206d9c2a48",
            "b_uuid": "b625be94-cf6e-4e54-b494-4155abcd9bbd",
            "p": [
                33.650001525878906,
                15.800000190734863
            ]
        },
        {
            "a_uuid": "b625be94-cf6e-4e54-b494-4155abcd9bbd",
            "b_uuid": "04ba9991-2069-4fa9-9f71-aae2db577742",
            "p": [
                31.299999237060547,
                15.149999618530273
            ]
        },
        {
            "a_uuid": "166841b5-9f81-440d-91d8-2f76b73cc446",
            "b_uuid": "b5f2b952-4563-4a78-9369-3029a97c1ec2",
            "p": [
                32.20000076293945,
                10.199999809265137
            ]
        }
    ]
}